dotmgr/__init__.py
dotmgr/cli.py
dotmgr/manager.py
dotmgr/paths.py
dotmgr/repository.py
dotmgr/transformer.py
dotmgr-0.5.3.dist-info/LICENSE
dotmgr-0.5.3.dist-info/METADATA
dotmgr-0.5.3.dist-info/WHEEL
dotmgr-0.5.3.dist-info/entry_points.txt
dotmgr-0.5.3.dist-info/top_level.txt
dotmgr-0.5.3.dist-info/RECORD
