Metadata-Version: 2.1
Name: dotmgr
Version: 0.5.3
Summary: A small script that can help you maintain your dotfiles across several devices
Author-email: Sebastian Neuser <haggl@sineband.de>
License: GNU GENERAL PUBLIC LICENSE
Project-URL: repository, https://gitlab.com/haggl/dotmgr
Project-URL: documentation, https://haggl.gitlab.io/dotmgr
Keywords: dotmgr,dotfile,management
Requires-Python: >=3.6
License-File: LICENSE
Requires-Dist: gitpython
Provides-Extra: dev
Requires-Dist: build ; extra == 'dev'
Requires-Dist: mypy ; extra == 'dev'
Requires-Dist: pylint ; extra == 'dev'
Requires-Dist: pytest-cov ; extra == 'dev'
Requires-Dist: recommonmark ; extra == 'dev'
Requires-Dist: sphinx ; extra == 'dev'
Requires-Dist: sphinx-pyproject ; extra == 'dev'
Requires-Dist: sphinx-rtd-theme ; extra == 'dev'
Requires-Dist: twine ; extra == 'dev'
